django_channel_tasks-1.4.0.dev1.data/data/bin/init-django-channel-tasks.sh
django_channel_tasks-1.4.0.dev1.data/data/bin/manage-unit.sh
django_channel_tasks-1.4.0.dev1.data/data/channel-tasks-docker/channel-tasks-unit.template.json
django_channel_tasks-1.4.0.dev1.data/data/channel-tasks-docker/django-runservers.sh
django_channel_tasks-1.4.0.dev1.dist-info/licenses/LICENSE
django_tasks/__init__.py
django_tasks/admin.py
django_tasks/admin_tools.py
django_tasks/apps.py
django_tasks/asgi_url_conf.py
django_tasks/authentication.py
django_tasks/consumers.py
django_tasks/django_setup.py
django_tasks/entrypoint.py
django_tasks/http_status.py
django_tasks/models.py
django_tasks/nginx_views.py
django_tasks/routing.py
django_tasks/scheduler.py
django_tasks/serializers.py
django_tasks/task_cache.py
django_tasks/task_inspector.py
django_tasks/task_runner.py
django_tasks/tasks.py
django_tasks/typing.py
django_tasks/urls.py
django_tasks/viewsets.py
django_tasks/wsgi.py
django_tasks/wsgi_url_conf.py
django_tasks/management/commands/__init__.py
django_tasks/management/commands/create_core_admin.py
django_tasks/migrations/0001_initial.py
django_tasks/migrations/__init__.py
django_tasks/settings/__init__.py
django_tasks/settings/asgi.py
django_tasks/settings/base.py
django_tasks/settings/wsgi.py
django_tasks/static/js/task_alerts.js
django_tasks/templates/admin_index.html
django_tasks/templates/task_alerts.html
django_tasks/testing/__init__.py
django_tasks/testing/request_cases.py
django_tasks/testing/websocket_test_client.py
django_tasks/websocket/__init__.py
django_tasks/websocket/backend_client.py
django_tasks/websocket/close_codes.py
django_channel_tasks-1.4.0.dev1.dist-info/METADATA
django_channel_tasks-1.4.0.dev1.dist-info/WHEEL
django_channel_tasks-1.4.0.dev1.dist-info/entry_points.txt
django_channel_tasks-1.4.0.dev1.dist-info/top_level.txt
django_channel_tasks-1.4.0.dev1.dist-info/RECORD
